pyjava/__init__.py
pyjava/cloudpickle.py
pyjava/daemon.py
pyjava/fix.py
pyjava/ray.py
pyjava/rayfix.py
pyjava/serializers.py
pyjava/test.py
pyjava/utils.py
pyjava/version.py
pyjava/worker.py
pyjava/api/__init__.py
pyjava/api/mlsql.py
pyjava/api/ray_context.py
pyjava/api/serve.py
pyjava/cache/__init__.py
pyjava/cache/code_cache.py
pyjava/data/__init__.py
pyjava/data/datasource.py
pyjava/datatype/__init__.py
pyjava/datatype/types.py
pyjava/storage/__init__.py
pyjava/storage/streaming_tar.py
pyjava/udf/__init__.py
pyjava/udf/store.py
pyjava/udf/udf_builder.py
pyjava/udf/udf_master.py
pyjava/udf/udf_worker.py
pyjava-0.6.21.dist-info/METADATA
pyjava-0.6.21.dist-info/WHEEL
pyjava-0.6.21.dist-info/top_level.txt
pyjava-0.6.21.dist-info/RECORD
