Metadata-Version: 2.1
Name: pyjava
Version: 0.6.21
Summary: PyJava Python API
Home-page: https://github.com/allwefantasy/pyjava
Author: allwefantasy
Author-email: allwefantasy@gmail.com
License: http://www.apache.org/licenses/LICENSE-2.0
Classifier: Development Status :: 5 - Production/Stable
Classifier: License :: OSI Approved :: Apache Software License
Classifier: Programming Language :: Python :: 3.6
Classifier: Programming Language :: Python :: 3.7
Classifier: Programming Language :: Python :: Implementation :: CPython
Classifier: Programming Language :: Python :: Implementation :: PyPy
